<?xml version="1.0" encoding="UTF-8" standalone="no"?>
<!-- Generated Jan 10, 2018 10:42:17 AM by Hibernate Tools 5.2.3.Final --><!DOCTYPE hibernate-mapping PUBLIC "-//Hibernate/Hibernate Mapping DTD 3.0//EN" "http://www.hibernate.org/dtd/hibernate-mapping-3.0.dtd">
<hibernate-mapping auto-import="true" default-access="property" default-cascade="none" default-lazy="true">
    <class catalog="jdbc_certification" dynamic-insert="false" dynamic-update="false" mutable="true" name="com.reverse.CertificationTechnology" optimistic-lock="version" polymorphism="implicit" select-before-update="false" table="certification_technology">
        <id name="id" type="int">
            <column name="id"/>
            <generator class="assigned"/>
        </id>
        <property generated="never" lazy="false" name="certificationName" optimistic-lock="true" type="string" unique="false">
            <column length="200" name="certification_name"/>
        </property>
        <property generated="never" lazy="false" name="certificationDescription" optimistic-lock="true" type="string" unique="false">
            <column length="200" name="certification_description"/>
        </property>
        <property generated="never" lazy="false" name="certificationCategory" optimistic-lock="true" type="string" unique="false">
            <column length="45" name="certification_category"/>
        </property>
        <set embed-xml="true" fetch="select" inverse="true" lazy="true" mutable="true" name="userScorecards" optimistic-lock="true" sort="unsorted" table="user_scorecard">
            <key on-delete="noaction">
                <column name="certification_id"/>
            </key>
            <one-to-many class="com.reverse.UserScorecard" embed-xml="true" not-found="exception"/>
        </set>
        <set embed-xml="true" fetch="select" inverse="true" lazy="true" mutable="true" name="examinationSlots" optimistic-lock="true" sort="unsorted" table="examination_slot">
            <key on-delete="noaction">
                <column name="certification_id"/>
            </key>
            <one-to-many class="com.reverse.ExaminationSlot" embed-xml="true" not-found="exception"/>
        </set>
    </class>
</hibernate-mapping>
